{"records":[{"id":"4227a75a-e796-46f1-83b6-0caf07e64527","organizationId":"pw-org","employeeNumber":"PW1001","displayName":"Playwright Alpha Employee","employmentStatus":"draft","legalName":"Playwright Alpha Employee","preferredName":null,"departmentName":null,"positionTitle":null,"employmentStartDate":null,"employmentType":"","workerCategory":"","grade":"","level":"","legalEntityCode":"","workLocationCode":"","countryCode":"","contractStartDate":null,"contractEndDate":null,"currentDepartmentId":null,"currentPositionId":null,"managerEmployeeId":null,"matrixManagerEmployeeId":null,"hrOwnerEmployeeId":null,"assignmentHistory":[],"auditTrail":[{"id":"ea63022a-84cd-4220-9198-fd63316e9b57","organizationId":"pw-org","employeeId":"4227a75a-e796-46f1-83b6-0caf07e64527","action":"hr.employees.employee.created","actorId":null,"reason":"Initial create","createdAt":"2026-06-09T21:22:56.293Z","updatedAt":"2026-06-09T21:22:56.293Z"}],"statusHistory":[{"id":"91d3fe3f-c588-4d6a-b96c-6e88afdd6b6a","organizationId":"pw-org","employeeId":"4227a75a-e796-46f1-83b6-0caf07e64527","status":"draft","previousStatus":null,"effectiveAt":"2026-06-09T21:22:56.293Z","source":"create","reason":"Initial status","actorId":null,"createdAt":"2026-06-09T21:22:56.293Z","updatedAt":"2026-06-09T21:22:56.293Z"}],"email":"pw.alpha@example.com","identityNumber":"","identityDocumentType":"","nationality":"","phoneNumber":"","personalEmail":"","dateOfBirth":null,"gender":"","maritalStatus":"","languagePreference":"","residentialAddress":"","mailingAddress":"","emergencyContactName":"","emergencyContactRelationship":"","emergencyContactPhoneNumber":"","createdAt":"2026-06-09T21:22:56.293Z","updatedAt":"2026-06-09T21:22:56.293Z"},{"id":"79f38b5b-7986-4809-a2a7-0154dd062d1f","organizationId":"pw-org","employeeNumber":"PW1002","displayName":"Playwright Beta Employee","employmentStatus":"draft","legalName":"Playwright Beta Employee","preferredName":null,"departmentName":null,"positionTitle":null,"employmentStartDate":null,"employmentType":"","workerCategory":"","grade":"","level":"","legalEntityCode":"","workLocationCode":"","countryCode":"","contractStartDate":null,"contractEndDate":null,"currentDepartmentId":null,"currentPositionId":null,"managerEmployeeId":null,"matrixManagerEmployeeId":null,"hrOwnerEmployeeId":null,"assignmentHistory":[],"auditTrail":[{"id":"42f8e38b-7ad4-4e08-abcd-a0484ca293fb","organizationId":"pw-org","employeeId":"79f38b5b-7986-4809-a2a7-0154dd062d1f","action":"hr.employees.employee.created","actorId":null,"reason":"Initial create","createdAt":"2026-06-09T21:22:56.370Z","updatedAt":"2026-06-09T21:22:56.370Z"}],"statusHistory":[{"id":"02eb054d-1ff0-461a-8dff-5557b044fd58","organizationId":"pw-org","employeeId":"79f38b5b-7986-4809-a2a7-0154dd062d1f","status":"draft","previousStatus":null,"effectiveAt":"2026-06-09T21:22:56.370Z","source":"create","reason":"Initial status","actorId":null,"createdAt":"2026-06-09T21:22:56.370Z","updatedAt":"2026-06-09T21:22:56.370Z"}],"email":"pw.beta@example.com","identityNumber":"","identityDocumentType":"","nationality":"","phoneNumber":"","personalEmail":"","dateOfBirth":null,"gender":"","maritalStatus":"","languagePreference":"","residentialAddress":"","mailingAddress":"","emergencyContactName":"","emergencyContactRelationship":"","emergencyContactPhoneNumber":"","createdAt":"2026-06-09T21:22:56.370Z","updatedAt":"2026-06-09T21:22:56.370Z"}]}